icao_nnumber_converter_us/__init__.py
icao_nnumber_converter_us/convert.py
icao_nnumber_converter_us-0.1.0.dist-info/LICENSE
icao_nnumber_converter_us-0.1.0.dist-info/METADATA
icao_nnumber_converter_us-0.1.0.dist-info/WHEEL
icao_nnumber_converter_us-0.1.0.dist-info/top_level.txt
icao_nnumber_converter_us-0.1.0.dist-info/RECORD
