Metadata-Version: 2.1
Name: icao-nnumber-converter-us
Version: 0.1.0
Summary: Script converting US issued ICAO addresses to N-Numbers (Tail Numbers) and reciprocally.
Home-page: https://github.com/guillaumemichel/icao-nnumber_converter
Author: Guillaume Michel
Author-email: millaume.guichel@gmail.com
License: UNKNOWN
Platform: UNKNOWN
Classifier: Programming Language :: Python :: 3
Classifier: License :: OSI Approved :: GNU General Public License v3 (GPLv3)
Classifier: Operating System :: OS Independent
Requires-Python: >=3.6
